dtpyredis/__init__.py
dtpyredis/caching.py
dtpyredis/config.py
dtpyredis/connection.py
dtpyredis/health.py
dtpyredis-1.0.1.dist-info/METADATA
dtpyredis-1.0.1.dist-info/WHEEL
dtpyredis-1.0.1.dist-info/RECORD
