Metadata-Version: 2.3
Name: dtpyredis
Version: 1.0.1
Summary: A light python package for redis management.
License: MIT
Author: Reza Shirazi
Author-email: reza@datgate.com
Requires-Python: >=3.11.9,<3.12.0
Classifier: License :: OSI Approved :: MIT License
Classifier: Programming Language :: Python :: 3
Requires-Dist: dtpyutils (>=1.0.0,<1.1.0)
Requires-Dist: redis (>=5.2.1,<5.3.0)
